spacy_llm/__init__.py
spacy_llm/cache.py
spacy_llm/compat.py
spacy_llm/ty.py
spacy_llm/util.py
spacy_llm/models/__init__.py
spacy_llm/models/hf/__init__.py
spacy_llm/models/hf/base.py
spacy_llm/models/hf/dolly.py
spacy_llm/models/hf/falcon.py
spacy_llm/models/hf/llama2.py
spacy_llm/models/hf/mistral.py
spacy_llm/models/hf/openllama.py
spacy_llm/models/hf/stablelm.py
spacy_llm/models/langchain/__init__.py
spacy_llm/models/langchain/model.py
spacy_llm/models/rest/__init__.py
spacy_llm/models/rest/base.py
spacy_llm/models/rest/anthropic/__init__.py
spacy_llm/models/rest/anthropic/model.py
spacy_llm/models/rest/anthropic/registry.py
spacy_llm/models/rest/azure/__init__.py
spacy_llm/models/rest/azure/model.py
spacy_llm/models/rest/azure/registry.py
spacy_llm/models/rest/cohere/__init__.py
spacy_llm/models/rest/cohere/model.py
spacy_llm/models/rest/cohere/registry.py
spacy_llm/models/rest/noop/__init__.py
spacy_llm/models/rest/noop/model.py
spacy_llm/models/rest/noop/registry.py
spacy_llm/models/rest/openai/__init__.py
spacy_llm/models/rest/openai/model.py
spacy_llm/models/rest/openai/registry.py
spacy_llm/models/rest/palm/__init__.py
spacy_llm/models/rest/palm/model.py
spacy_llm/models/rest/palm/registry.py
spacy_llm/pipeline/__init__.py
spacy_llm/pipeline/llm.py
spacy_llm/registry/__init__.py
spacy_llm/registry/normalizer.py
spacy_llm/registry/reader.py
spacy_llm/registry/util.py
spacy_llm/tasks/__init__.py
spacy_llm/tasks/builtin_task.py
spacy_llm/tasks/noop.py
spacy_llm/tasks/entity_linker/__init__.py
spacy_llm/tasks/entity_linker/candidate_selector.py
spacy_llm/tasks/entity_linker/parser.py
spacy_llm/tasks/entity_linker/registry.py
spacy_llm/tasks/entity_linker/task.py
spacy_llm/tasks/entity_linker/ty.py
spacy_llm/tasks/entity_linker/util.py
spacy_llm/tasks/lemma/__init__.py
spacy_llm/tasks/lemma/parser.py
spacy_llm/tasks/lemma/registry.py
spacy_llm/tasks/lemma/task.py
spacy_llm/tasks/lemma/util.py
spacy_llm/tasks/ner/__init__.py
spacy_llm/tasks/ner/registry.py
spacy_llm-0.7.2.dist-info/LICENSE
spacy_llm-0.7.2.dist-info/METADATA
spacy_llm-0.7.2.dist-info/WHEEL
spacy_llm-0.7.2.dist-info/entry_points.txt
spacy_llm-0.7.2.dist-info/top_level.txt
spacy_llm-0.7.2.dist-info/RECORD
