Metadata-Version: 2.1
Name: spacy-llm
Version: 0.7.2
Summary: Integrating LLMs into structured NLP pipelines
Author: Explosion
Author-email: contact@explosion.ai
License: MIT
Project-URL: Release notes, https://github.com/explosion/spacy-llm/releases
Project-URL: Source, https://github.com/explosion/spacy-llm
Classifier: Development Status :: 4 - Beta
Classifier: Environment :: Console
Classifier: Intended Audience :: Developers
Classifier: Intended Audience :: Science/Research
Classifier: License :: OSI Approved :: MIT License
Classifier: Operating System :: POSIX :: Linux
Classifier: Operating System :: MacOS :: MacOS X
Classifier: Operating System :: Microsoft :: Windows
Classifier: Programming Language :: Python :: 3
Classifier: Programming Language :: Python :: 3.7
Classifier: Programming Language :: Python :: 3.8
Classifier: Programming Language :: Python :: 3.9
Classifier: Programming Language :: Python :: 3.10
Classifier: Programming Language :: Python :: 3.11
Classifier: Programming Language :: Python :: 3.12
Classifier: Topic :: Scientific/Engineering
Requires-Python: >=3.7
License-File: LICENSE
Requires-Dist: spacy <4.0,>=3.5
Requires-Dist: jinja2
Requires-Dist: confection <1.0.0,>=0.1.3
Provides-Extra: langchain
Requires-Dist: langchain <0.2,>=0.1 ; extra == 'langchain'
Provides-Extra: transformers
Requires-Dist: torch <2.0,>=1.13.1 ; extra == 'transformers'
Requires-Dist: transformers <5.0,>=4.28.1 ; extra == 'transformers'
Requires-Dist: einops >=0.4 ; extra == 'transformers'
Requires-Dist: xformers ; extra == 'transformers'
